django_uwsgi/__init__.py
django_uwsgi/admin.py
django_uwsgi/apps.py
django_uwsgi/cache.py
django_uwsgi/mail.py
django_uwsgi/panels.py
django_uwsgi/stats.py
django_uwsgi/tasks.py
django_uwsgi/urls.py
django_uwsgi/views.py
django_uwsgi/wagtail_hooks.py
django_uwsgi/emperor/__init__.py
django_uwsgi/emperor/admin.py
django_uwsgi/emperor/apps.py
django_uwsgi/emperor/models.py
django_uwsgi/emperor/wagtail_hooks.py
django_uwsgi/emperor/migrations/0001_initial.py
django_uwsgi/emperor/migrations/__init__.py
django_uwsgi/templates/uwsgi/actions.html
django_uwsgi/templates/uwsgi/applications.html
django_uwsgi/templates/uwsgi/jobs.html
django_uwsgi/templates/uwsgi/magic_table.html
django_uwsgi/templates/uwsgi/options.html
django_uwsgi/templates/uwsgi/status.html
django_uwsgi/templates/uwsgi/unavailable.html
django_uwsgi/templates/uwsgi/wagtail_dashboard_item.html
django_uwsgi/templates/uwsgi/workers.html
django_uwsgi/templates/uwsgi/common/actions.html
django_uwsgi/templates/uwsgi/common/workers.html
django_uwsgi/templates/uwsgi/panels/actions.html
django_uwsgi_admin-2.0.1.dist-info/AUTHORS.rst
django_uwsgi_admin-2.0.1.dist-info/LICENSE
django_uwsgi_admin-2.0.1.dist-info/METADATA
django_uwsgi_admin-2.0.1.dist-info/WHEEL
django_uwsgi_admin-2.0.1.dist-info/top_level.txt
django_uwsgi_admin-2.0.1.dist-info/RECORD
