Metadata-Version: 2.1
Name: django-uwsgi-admin
Version: 2.0.1
Summary: Django related examples/tricks/modules for uWSGI.
Home-page: https://github.com/ionelmc/django-uwsgi-admin
Author: Eugene MechanisM
Author-email: eugene@mechanism.pro
Maintainer: Ionel Cristian Maries
Maintainer-email: contact@ionelmc.ro
License: MIT
Project-URL: Documentation, https://django-uwsgi-admin.readthedocs.io/
Project-URL: Changelog, https://django-uwsgi-admin.readthedocs.io/en/latest/changelog.html
Project-URL: Issue Tracker, https://github.com/ionelmc/django-uwsgi-admin/issues
Keywords: uwsgi,django,mail,cache,template
Platform: UNKNOWN
Classifier: Development Status :: 5 - Production/Stable
Classifier: Intended Audience :: Developers
Classifier: Intended Audience :: System Administrators
Classifier: License :: OSI Approved :: MIT License
Classifier: Operating System :: Unix
Classifier: Operating System :: POSIX
Classifier: Programming Language :: Python
Classifier: Programming Language :: Python :: 3
Classifier: Programming Language :: Python :: 3 :: Only
Classifier: Programming Language :: Python :: 3.7
Classifier: Programming Language :: Python :: 3.8
Classifier: Programming Language :: Python :: 3.9
Classifier: Programming Language :: Python :: 3.10
Classifier: Programming Language :: Python :: 3.11
Classifier: Programming Language :: Python :: Implementation :: CPython
Classifier: Programming Language :: Python :: Implementation :: PyPy
Classifier: Framework :: Django
Classifier: Framework :: Django :: 3.2
Classifier: Framework :: Django :: 4.0
Classifier: Framework :: Django :: 4.1
Classifier: Topic :: Software Development :: Libraries :: Python Modules
Classifier: Topic :: Internet :: WWW/HTTP :: WSGI
Classifier: Topic :: Internet :: WWW/HTTP :: WSGI :: Application
Classifier: Topic :: Internet :: WWW/HTTP :: Dynamic Content
Classifier: Topic :: Internet :: WWW/HTTP :: Site Management
Classifier: Topic :: Software Development :: Build Tools
Classifier: Topic :: Software Development :: Code Generators
Classifier: Topic :: Communications :: Email
Classifier: Framework :: Django
Classifier: Topic :: Utilities
Requires-Python: >=3.7
License-File: LICENSE
License-File: AUTHORS.rst
Requires-Dist: django-admin-utils
Provides-Extra: uwsgi
Requires-Dist: uwsgi ; extra == 'uwsgi'
